tripper/__init__.py
tripper/errors.py
tripper/interface.py
tripper/literal.py
tripper/namespace.py
tripper/session.py
tripper/triplestore.py
tripper/triplestore_extend.py
tripper/utils.py
tripper/backends/__init__.py
tripper/backends/collection.py
tripper/backends/ontopy.py
tripper/backends/rdflib.py
tripper/backends/sparqlwrapper.py
tripper/context/0.2/context.json
tripper/context/0.3/context.json
tripper/context/0.3/keywords.yaml
tripper/context/process/0.1/context.json
tripper/context/process/0.1/keywords.yaml
tripper/convert/__init__.py
tripper/convert/convert.py
tripper/datadoc/__init__.py
tripper/datadoc/clitool.py
tripper/datadoc/context.py
tripper/datadoc/dataaccess.py
tripper/datadoc/dataset.py
tripper/datadoc/errors.py
tripper/datadoc/keywords.py
tripper/datadoc/tabledoc.py
tripper/mappings/__init__.py
tripper/mappings/mappings.py
tripper/units/__init__.py
tripper/units/units.py
tripper-0.4.3.dist-info/entry_points.txt
tripper-0.4.3.dist-info/licenses/LICENSE
tripper-0.4.3.dist-info/WHEEL
tripper-0.4.3.dist-info/METADATA
tripper-0.4.3.dist-info/RECORD
