Metadata-Version: 2.4
Name: tripper
Version: 0.4.3
Summary: A triplestore wrapper for Python.
Keywords: triplestore,ontology,RDF
Author-email: SINTEF <TEAM4.0@sintef.no>
Requires-Python: >=3.8
Classifier: Development Status :: 2 - Pre-Alpha
Classifier: License :: OSI Approved :: MIT License
Classifier: Programming Language :: Python :: 3
Classifier: Programming Language :: Python :: 3.8
Classifier: Programming Language :: Python :: 3.9
Classifier: Programming Language :: Python :: 3.10
Classifier: Programming Language :: Python :: 3.11
Classifier: Programming Language :: Python :: 3.12
Classifier: Programming Language :: Python :: 3.13
Classifier: Programming Language :: Python :: 3.14
Classifier: Environment :: Plugins
Classifier: Natural Language :: English
Classifier: Operating System :: OS Independent
License-File: LICENSE
Requires-Dist: typing-extensions>=4.7.0,<4.13.1; python_version < '3.9'
Requires-Dist: dlite-python>=0.5.27 ; extra == "backends" and ( python_version<='3.13')
Requires-Dist: emmontopy>=0.5.0,<0.7.1 ; extra == "backends" and ( python_version<'3.13')
Requires-Dist: graphviz>=0.20.1,<0.20.2 ; extra == "backends"
Requires-Dist: numpy<2.1.0 ; extra == "backends" and ( python_version=='3.13')
Requires-Dist: rdflib>=6.3.0,<7.0.0 ; extra == "backends"
Requires-Dist: tripper[mappings] ; extra == "datadoc"
Requires-Dist: PyLD>=2.0.0,<2.0.5 ; extra == "datadoc" and ( python_version<='3.13')
Requires-Dist: PyYaml>=3.0.0,<6.0.3 ; extra == "datadoc"
Requires-Dist: requests>=2.0.0,<3.4.1 ; extra == "datadoc"
Requires-Dist: sparqlwrapper>=2.0.0,<2.0.1 ; extra == "datadoc"
Requires-Dist: tripper[pre-commit, docs] ; extra == "dev"
Requires-Dist: tripper[testing] ; extra == "docs"
Requires-Dist: mike==2.1.3 ; extra == "docs"
Requires-Dist: mkdocs==1.6.1 ; extra == "docs"
Requires-Dist: mkdocs-autorefs==1.4.1 ; extra == "docs"
Requires-Dist: mkdocs-awesome-pages-plugin==2.10.1 ; extra == "docs"
Requires-Dist: mkdocs-github-admonitions-plugin==0.0.3 ; extra == "docs"
Requires-Dist: mkdocs-material==9.6.11 ; extra == "docs"
Requires-Dist: mkdocstrings==0.27.0 ; extra == "docs"
Requires-Dist: mkdocstrings-python-legacy==0.2.4 ; extra == "docs"
Requires-Dist: tripper[units] ; extra == "mappings"
Requires-Dist: pre-commit==4.0.1 ; extra == "pre-commit"
Requires-Dist: pylint==3.3.4 ; extra == "pre-commit" and ( python_version>='3.9')
Requires-Dist: tripper[datadoc, backends, testing-core] ; extra == "testing"
Requires-Dist: pytest==8.3.4 ; extra == "testing-core"
Requires-Dist: pytest-cov==5.0.0 ; extra == "testing-core" and ( python_version<'3.9')
Requires-Dist: pytest-cov==6.0.0 ; extra == "testing-core" and ( python_version>='3.9')
Requires-Dist: pint>=0.21.1,<0.26 ; extra == "units" and ( python_version<'3.9')
Requires-Dist: pint>=0.24.1,<0.26 ; extra == "units" and ( python_version>='3.9')
Requires-Dist: rdflib>=6.3.0,<7.0.0 ; extra == "units"
Project-URL: Changelog, https://github.com/EMMC-ASBL/tripper/blob/master/CHANGELOG.md
Project-URL: Documentation, https://EMMC-ASBL.github.io/tripper
Project-URL: Home, https://github.com/EMMC-ASBL/tripper
Project-URL: Issue Tracker, https://github.com/EMMC-ASBL/tripper/issues
Project-URL: Package, https://pypi.org/project/tripper
Project-URL: Source, https://github.com/EMMC-ASBL/tripper
Provides-Extra: backends
Provides-Extra: datadoc
Provides-Extra: dev
Provides-Extra: docs
Provides-Extra: mappings
Provides-Extra: pre-commit
Provides-Extra: testing
Provides-Extra: testing-core
Provides-Extra: units
